BlueWhale3_Text-1.6.0-py3.8-nspkg.pth
orangecontrib/text/__init__.py
orangecontrib/text/corpus.py
orangecontrib/text/corpus_to_network.py
orangecontrib/text/country_codes.py
orangecontrib/text/guardian.py
orangecontrib/text/i18n_config.py
orangecontrib/text/import_documents.py
orangecontrib/text/language_codes.py
orangecontrib/text/nyt.py
orangecontrib/text/pubmed.py
orangecontrib/text/stats.py
orangecontrib/text/tweet_profiler.py
orangecontrib/text/twitter.py
orangecontrib/text/util.py
orangecontrib/text/version.py
orangecontrib/text/wikipedia_api.py
orangecontrib/text/datasets/20newsgroups-test.tab
orangecontrib/text/datasets/20newsgroups-train.tab
orangecontrib/text/datasets/README.txt
orangecontrib/text/datasets/andersen.tab
orangecontrib/text/datasets/book-excerpts.tab
orangecontrib/text/datasets/deerwester.tab
orangecontrib/text/datasets/election-tweets-2016.tab
orangecontrib/text/datasets/friends-transcripts.tab
orangecontrib/text/datasets/grimm-tales-selected.tab
orangecontrib/text/datasets/grimm-tales.tab
orangecontrib/text/datasets/reuters-r52-test.tab
orangecontrib/text/datasets/reuters-r52-train.tab
orangecontrib/text/datasets/reuters-r8-test.tab
orangecontrib/text/datasets/reuters-r8-train.tab
orangecontrib/text/datasets/slo-opinion-corpus.tab
orangecontrib/text/keywords/__init__.py
orangecontrib/text/keywords/embedding.py
orangecontrib/text/keywords/rake.py
orangecontrib/text/locale/text.en.yml
orangecontrib/text/locale/text.zh.yml
orangecontrib/text/misc/__init__.py
orangecontrib/text/misc/nltk_data_download.py
orangecontrib/text/preprocess/__init__.py
orangecontrib/text/preprocess/filter.py
orangecontrib/text/preprocess/normalize.py
orangecontrib/text/preprocess/preprocess.py
orangecontrib/text/preprocess/tokenize.py
orangecontrib/text/preprocess/transform.py
orangecontrib/text/sentiment/__init__.py
orangecontrib/text/sentiment/filter_lexicon.py
orangecontrib/text/sentiment/resources/negative_words_Slolex.txt
BlueWhale3_Text-1.6.0.dist-info/LICENSE
BlueWhale3_Text-1.6.0.dist-info/METADATA
BlueWhale3_Text-1.6.0.dist-info/WHEEL
BlueWhale3_Text-1.6.0.dist-info/entry_points.txt
BlueWhale3_Text-1.6.0.dist-info/namespace_packages.txt
BlueWhale3_Text-1.6.0.dist-info/top_level.txt
BlueWhale3_Text-1.6.0.dist-info/RECORD
